MANIFEST.in
README.md
setup.py
docker_sync/Manager.py
docker_sync/TestManager.py
docker_sync/__init__.py
docker_sync/__main__.py
docker_sync/cli.py
docker_sync.egg-info/PKG-INFO
docker_sync.egg-info/SOURCES.txt
docker_sync.egg-info/dependency_links.txt
docker_sync.egg-info/entry_points.txt
docker_sync.egg-info/requires.txt
docker_sync.egg-info/top_level.txt
docker_sync/lib/Container.py
docker_sync/lib/ContainerDefinition.py
docker_sync/lib/DockerSyncWrapper.py
docker_sync/lib/Image.py
docker_sync/lib/ImageTag.py
docker_sync/lib/TestContainerDefinition.py
docker_sync/lib/TestDockerSyncWrapper.py
docker_sync/lib/TestImage.py
docker_sync/lib/TestImageTag.py
docker_sync/lib/__init__.py