Metadata-Version: 1.0
Name: docker-sync
Version: 1.1.0
Summary: Configuration management for Docker containers
Home-page: http://github.com/autosportlabs/docker-sync
Author: Brian Lalor
Author-email: brian@autosportlabs.com
License: UNKNOWN
Platform: UNKNOWN
